Workbook

Sheet Overview
A1: CONTASPICCIOLI 2026
A3: LEGENDA
A4: Celle verdi = input globali (modifica con cura)
A5: Celle rosse = input mensili/simulazioni
A6: Celle blu = formule automatiche (non toccare)
A8: PARAMETRI BUDGET 2026 | E8: IMPOSTAZIONI P.IVA FORFETTARIA
A10: Entrata mensile prevista | B10: 3500 | C10: € | E10: Aliquota INPS | F10: 0.2598
E11: Coeff. redditività | F11: 0.78
A12: Voce | B12: Percentuale | C12: €/mese | E12: Aliquota fiscale | F12: 0.05
A13: Spese fisse | B13: 0.3337 | C13: =B10*B13
A14: Spese variabili | B14: 0.2546 | C14: =B10*B14
A15: XEON tasse (3° pilastro) | B15: 0.3143 | C15: =B10*B15
A16: ETF investimenti (4° pilastro) | B16: 0.0974 | C16: =B10*B16
A17: Totale | B17: =SUM(B13:B16) | C17: =SUM(C13:C16)
A20: SIMULATORE
A21: Inserisci importo per simulare divisione: | B21: 3500
A23: Spese fisse | B23: =B21*B13
A24: Spese variabili | B24: =B21*B14
A25: XEON tasse | B25: =B21*B15
A26: ETF investimenti | B26: =B21*B16

Sheet 4 Pilastri
A1: I 4 PILASTRI DEL BUDGET 2026
A3: Pilastro | B3: Saldo Iniziale | C3: Accantonato YTD | D3: Prelievi YTD | E3: Saldo Teorico | F3: Saldo Reale | G3: Differenza
A4: 1° Conto corrente | B4: 5958.57 | C4: =Overview!C13+Overview!C14 | D4: 0 | E4: =B4+C4-D4 | F4: 0 | G4: =F4-E4
A5: 2° XEON emergenza | B5: 10000 | C5: 0 | D5: 0 | E5: =B5+C5-D5 | F5: 0 | G5: =F5-E5
A6: 3° XEON tasse | B6: 3000 | C6: =Overview!C15*12 | D6: 12987 | E6: =B6+C6-D6 | F6: 0 | G6: =F6-E6
A7: 4° ETF investimenti | B7: 0 | C7: =Overview!C16*12 | D7: 0 | E7: =B7+C7-D7 | F7: 0 | G7: =F7-E7
A8: TOTALE PATRIMONIO | E8: =SUM(E4:E7) | F8: =SUM(F4:F7)
A11: RICONCILIAZIONE MENSILE
A13: Data ultima riconciliazione: | B13: 01/01/2026
A15: Note:
A16: - Inserisci il saldo reale nella colonna F dopo aver verificato i conti
A17: - La colonna G mostra la differenza tra teorico e reale
A18: - Differenze positive = hai più del previsto
A19: - Differenze negative = hai meno del previsto

Sheet Scadenze Fiscali
A1: SCADENZE FISCALI 2026
A3: Scadenza | B3: Data | C3: Importo Dovuto | D3: Pagato | E3: Residuo | F3: Stato
A4: Saldo + 1° acconto 2025 | B4: 30/06/2026 | C4: 7527 | D4: 0 | E4: =C4-D4 | F4: =IF(D4>=C4,"PAGATO","DA PAGARE")
A5: 2° acconto 2025 | B5: 30/11/2026 | C5: 5460 | D5: 0 | E5: =C5-D5 | F5: =IF(D5>=C5,"PAGATO","DA PAGARE")
A7: TOTALE | C7: =SUM(C4:C5) | D7: =SUM(D4:D5) | E7: =SUM(E4:E5)
A10: ACCANTONAMENTO TASSE
A12: Saldo XEON tasse (3° pilastro): | B12: ='4 Pilastri'!E6
A13: Tasse da pagare: | B13: =E7
A14: Copertura: | B14: =B12/B13
A15: Mancante: | B15: =MAX(0,B13-B12)

Sheet Categorie
A1: CATEGORIE SPESE
A3: SPESE FISSE
A4: Categoria | B4: Budget Mensile | C4: Icona
A5: Affitto | B5: 700 | C5: 🏠
A6: Palestra | B6: 35 | C6: 💪
A7: Commercialista | B7: 25 | C7: 📋
A8: Totale spese fisse: | B8: =SUM(B5:B7)
A11: SPESE VARIABILI
A12: Categoria | B12: Budget Mensile | C12: Icona
A13: Spesa alimentare | B13: 200 | C13: 🛒
A14: Trasporti | B14: 40 | C14: 🚌
A15: Servizi Digitali | B15: 15 | C15: 💻
A16: Ristoranti | B16: 290 | C16: 🍽️
A17: Cultura | B17: 35 | C17: 🎭
A18: Shopping | B18: 230 | C18: 🛍️
A19: Salute | B19: 380 | C19: ⚕️
A20: Contanti | B20: 100 | C20: 💵
A21: Totale spese variabili: | B21: =SUM(B13:B20)
A23: TOTALE BUDGET SPESE: | B23: =B8+B21

Sheet 2026 - Previsionale
A1: PREVISIONALE 2026
B3: EREDITÀ | C3: Gen | D3: Feb | E3: Mar | F3: Apr | G3: Mag | H3: Giu | I3: Lug | J3: Ago | K3: Set | L3: Ott | M3: Nov | N3: Dic | O3: TOTALE
A4: RICAVI
A5: Conto in banca | B5: 5958.57 | O5: =B5
A6: Ufficio Furore | C6: =Overview!$B$10 | D6: =Overview!$B$10 | E6: =Overview!$B$10 | F6: =Overview!$B$10 | G6: =Overview!$B$10 | H6: =Overview!$B$10 | I6: =Overview!$B$10 | J6: =Overview!$B$10 | ... N6: =Overview!$B$10 | O6: =SUM(C6:N6)
A7: Altre entrate | C7: 0 | D7: 0 | E7: 0 | F7: 0 | G7: 0 | H7: 0 | I7: 0 | J7: 0 | K7: 0 | L7: 0 | M7: 0 | N7: 0 | O7: =SUM(C7:N7)
A8: TOTALE RICAVI | B8: =B5 | C8: =SUM(C6:C7) | D8: =SUM(D6:D7) | E8: =SUM(E6:E7) | F8: =SUM(F6:F7) | G8: =SUM(G6:G7) | H8: =SUM(H6:H7) | I8: =SUM(I6:I7) | J8: =SUM(J6:J7) | ... N8: =SUM(N6:N7) | O8: =B8+SUM(C8:N8)
A10: SPESE FISSE
A11: Affitto | C11: 700 | D11: 700 | E11: 700 | F11: 700 | G11: 700 | H11: 700 | I11: 700 | J11: 700 | K11: 700 | L11: 700 | M11: 700 | N11: 700 | O11: =SUM(C11:N11)
A12: Palestra | C12: 350 | D12: 0 | E12: 0 | F12: 0 | G12: 0 | H12: 0 | I12: 0 | J12: 0 | K12: 0 | L12: 400 | M12: 0 | N12: 0 | O12: =SUM(C12:N12)
A13: Commercialista | C13: 300 | D13: 0 | E13: 0 | F13: 0 | G13: 0 | H13: 0 | I13: 0 | J13: 0 | K13: 0 | L13: 0 | M13: 0 | N13: 0 | O13: =SUM(C13:N13)
A14: IVA 2025 (Giugno) | C14: 0 | D14: 0 | E14: 0 | F14: 0 | G14: 0 | H14: 7527 | I14: 0 | J14: 0 | K14: 0 | L14: 0 | M14: 0 | N14: 0 | O14: =SUM(C14:N14)
A15: IVA 2025 (Novembre) | C15: 0 | D15: 0 | E15: 0 | F15: 0 | G15: 0 | H15: 0 | I15: 0 | J15: 0 | K15: 0 | L15: 0 | M15: 5460 | N15: 0 | O15: =SUM(C15:N15)
A16: Accantonamento XEON tasse | C16: =Overview!$C$15 | D16: =Overview!$C$15 | E16: =Overview!$C$15 | F16: =Overview!$C$15 | G16: =Overview!$C$15 | H16: =Overview!$C$15 | I16: =Overview!$C$15 | J16: =Overview!$C$15 | ... N16: =Overview!$C$15 | O16: =SUM(C16:N16)
A17: Accantonamento ETF | C17: =Overview!$C$16 | D17: =Overview!$C$16 | E17: =Overview!$C$16 | F17: =Overview!$C$16 | G17: =Overview!$C$16 | H17: =Overview!$C$16 | I17: =Overview!$C$16 | J17: =Overview!$C$16 | ... N17: =Overview!$C$16 | O17: =SUM(C17:N17)
A18: TOTALE SPESE FISSE | C18: =SUM(C11:C17) | D18: =SUM(D11:D17) | E18: =SUM(E11:E17) | F18: =SUM(F11:F17) | G18: =SUM(G11:G17) | H18: =SUM(H11:H17) | I18: =SUM(I11:I17) | J18: =SUM(J11:J17) | ... O18: =SUM(O11:O17)
A20: SPESE VARIABILI
A21: Spesa alimentare | C21: 200 | D21: 200 | E21: 200 | F21: 200 | G21: 200 | H21: 200 | I21: 200 | J21: 200 | K21: 200 | L21: 200 | M21: 200 | N21: 200 | O21: =SUM(C21:N21)
A22: Trasporti | C22: 40 | D22: 40 | E22: 40 | F22: 40 | G22: 40 | H22: 40 | I22: 40 | J22: 40 | K22: 40 | L22: 40 | M22: 40 | N22: 40 | O22: =SUM(C22:N22)
A23: Servizi Digitali | C23: 15 | D23: 15 | E23: 15 | F23: 15 | G23: 15 | H23: 15 | I23: 15 | J23: 15 | K23: 15 | L23: 15 | M23: 15 | N23: 15 | O23: =SUM(C23:N23)
A24: Ristoranti | C24: 290 | D24: 290 | E24: 290 | F24: 290 | G24: 290 | H24: 290 | I24: 290 | J24: 290 | K24: 290 | L24: 290 | M24: 290 | N24: 290 | O24: =SUM(C24:N24)
A25: Cultura | C25: 35 | D25: 35 | E25: 35 | F25: 35 | G25: 35 | H25: 35 | I25: 35 | J25: 35 | K25: 35 | L25: 35 | M25: 35 | N25: 35 | O25: =SUM(C25:N25)
A26: Shopping | C26: 230 | D26: 230 | E26: 230 | F26: 230 | G26: 230 | H26: 230 | I26: 230 | J26: 230 | K26: 230 | L26: 230 | M26: 230 | N26: 230 | O26: =SUM(C26:N26)
A27: Salute | C27: 380 | D27: 380 | E27: 380 | F27: 380 | G27: 380 | H27: 380 | I27: 380 | J27: 380 | K27: 380 | L27: 380 | M27: 380 | N27: 380 | O27: =SUM(C27:N27)
A28: Contanti | C28: 100 | D28: 100 | E28: 100 | F28: 100 | G28: 100 | H28: 100 | I28: 100 | J28: 100 | K28: 100 | L28: 100 | M28: 100 | N28: 100 | O28: =SUM(C28:N28)
A29: TOTALE SPESE VARIABILI | C29: =SUM(C21:C28) | D29: =SUM(D21:D28) | E29: =SUM(E21:E28) | F29: =SUM(F21:F28) | G29: =SUM(G21:G28) | H29: =SUM(H21:H28) | I29: =SUM(I21:I28) | J29: =SUM(J21:J28) | ... O29: =SUM(O21:O28)
A31: RIEPILOGO
A32: Totale Costi | C32: =C18+C28 | D32: =D18+D28 | E32: =E18+E28 | F32: =F18+F28 | G32: =G18+G28 | H32: =H18+H28 | I32: =I18+I28 | J32: =J18+J28 | ... O32: =O18+O28
A33: Saldo Mensile | C33: =C8-C32 | D33: =D8-D32 | E33: =E8-E32 | F33: =F8-F32 | G33: =G8-G32 | H33: =H8-H32 | I33: =I8-I32 | J33: =J8-J32 | ... N33: =N8-N32
A34: Saldo Cumulativo | B34: =B5 | C34: =B34+C33 | D34: =C34+D33 | E34: =D34+E33 | F34: =E34+F33 | G34: =F34+G33 | H34: =G34+H33 | I34: =H34+I33 | J34: =I34+J33 | ... N34: =M34+N33
